charmlibs/apt/__init__.py
charmlibs/apt/py.typed
charmlibs_apt-1.0.0.post0.dist-info/METADATA
charmlibs_apt-1.0.0.post0.dist-info/WHEEL
charmlibs_apt-1.0.0.post0.dist-info/RECORD
