Metadata-Version: 2.4
Name: charmlibs-apt
Version: 1.0.0.post0
Summary: A Pythonic interface to manage `apt` packages.
Project-URL: Documentation, https://documentation.ubuntu.com/charmlibs/reference/charmlibs/apt/
Project-URL: Repository, https://github.com/canonical/charmlibs
Project-URL: Issues, https://github.com/canonical/charmlibs/issues
Project-URL: Changelog, https://github.com/canonical/charmlibs/blob/main/apt/CHANGELOG.md
Author: The Charm Tech team at Canonical Ltd.
Classifier: Development Status :: 5 - Production/Stable
Classifier: Intended Audience :: Developers
Classifier: License :: OSI Approved :: Apache Software License
Classifier: Operating System :: POSIX :: Linux
Classifier: Programming Language :: Python :: 3
Requires-Python: >=3.10
Requires-Dist: opentelemetry-api
